dblocks_plugin/jahero_plugin/__init__.py
dblocks_plugin/jahero_plugin/cc.py
dblocks_plugin/jahero_plugin/deploy.py
dblocks_plugin/jahero_plugin/plug_config.py
dblocks_plugin/jahero_plugin/plug_model.py
d_blocks_core_plugin_jahero-0.3.0.4.dist-info/METADATA
d_blocks_core_plugin_jahero-0.3.0.4.dist-info/WHEEL
d_blocks_core_plugin_jahero-0.3.0.4.dist-info/RECORD
