Metadata-Version: 2.1
Name: d-blocks-core-plugin-jahero
Version: 0.3.0.4
Summary: Plugins that I use daily in my work.
License: MIT
Author: Jan Herout
Author-email: jan.herout@gmail.com
Requires-Python: >=3.11
Classifier: License :: OSI Approved :: MIT License
Classifier: Programming Language :: Python :: 3
Classifier: Programming Language :: Python :: 3.11
Classifier: Programming Language :: Python :: 3.12
Requires-Dist: d-blocks-core (>=0.9.3.7)
Requires-Dist: tomlkit (>=0.13.2,<0.14.0)
